Thymeleaf30ZhongwenWendang/README.md
Thymeleaf30ZhongwenWendang/__init__.py
Thymeleaf30ZhongwenWendang/__main__.py
Thymeleaf30ZhongwenWendang/file.epub
Thymeleaf30ZhongwenWendang/index.html
Thymeleaf30ZhongwenWendang/css/__init__.py
Thymeleaf30ZhongwenWendang/css/annotations.css
Thymeleaf30ZhongwenWendang/css/main.css
Thymeleaf30ZhongwenWendang/css/normalize.css
Thymeleaf30ZhongwenWendang/css/popup.css
Thymeleaf30ZhongwenWendang/font/__init__.py
Thymeleaf30ZhongwenWendang/font/fontello.eot
Thymeleaf30ZhongwenWendang/font/fontello.svg
Thymeleaf30ZhongwenWendang/font/fontello.ttf
Thymeleaf30ZhongwenWendang/font/fontello.woff
Thymeleaf30ZhongwenWendang/img/__init__.py
Thymeleaf30ZhongwenWendang/img/annotator-glyph-sprite.png
Thymeleaf30ZhongwenWendang/img/annotator-icon-sprite.png
Thymeleaf30ZhongwenWendang/img/apple-touch-icon.png
Thymeleaf30ZhongwenWendang/img/cancelfullscreen.png
Thymeleaf30ZhongwenWendang/img/close.png
Thymeleaf30ZhongwenWendang/img/fullscreen.png
Thymeleaf30ZhongwenWendang/img/loader.gif
Thymeleaf30ZhongwenWendang/img/menu-icon.png
Thymeleaf30ZhongwenWendang/img/save.png
Thymeleaf30ZhongwenWendang/img/saved.png
Thymeleaf30ZhongwenWendang/img/settings-s.png
Thymeleaf30ZhongwenWendang/img/settings.png
Thymeleaf30ZhongwenWendang/img/star.png
Thymeleaf30ZhongwenWendang/js/__init__.py
Thymeleaf30ZhongwenWendang/js/epub.js
Thymeleaf30ZhongwenWendang/js/epub.min.js
Thymeleaf30ZhongwenWendang/js/epub.min.map
Thymeleaf30ZhongwenWendang/js/hooks.min.js
Thymeleaf30ZhongwenWendang/js/hooks.min.map
Thymeleaf30ZhongwenWendang/js/reader.js
Thymeleaf30ZhongwenWendang/js/reader.js.map
Thymeleaf30ZhongwenWendang/js/reader.min.js
Thymeleaf30ZhongwenWendang/js/reader.min.map
Thymeleaf30ZhongwenWendang/js/hooks/__init__.py
Thymeleaf30ZhongwenWendang/js/hooks/extensions/__init__.py
Thymeleaf30ZhongwenWendang/js/hooks/extensions/highlight.js
Thymeleaf30ZhongwenWendang/js/libs/__init__.py
Thymeleaf30ZhongwenWendang/js/libs/jquery.min.js
thymeleaf_3_0_zhongwen_wendang-2024.3.5.0.dist-info/METADATA
thymeleaf_3_0_zhongwen_wendang-2024.3.5.0.dist-info/WHEEL
thymeleaf_3_0_zhongwen_wendang-2024.3.5.0.dist-info/entry_points.txt
thymeleaf_3_0_zhongwen_wendang-2024.3.5.0.dist-info/top_level.txt
thymeleaf_3_0_zhongwen_wendang-2024.3.5.0.dist-info/RECORD
